slash/__init__.py
slash/cli.py
slash/daemon.py
slash/docstrings.py
slash/slash.py
slash/utils.py
slash/core/__init__.py
slash/core/config.py
slash/core/constants.py
slash/core/envs.py
slash/core/initialize.py
slash/core/service.py
slash/core/shell.py
slash_py-0.0.2.dist-info/licenses/LICENSE
slash_py-0.0.2.dist-info/METADATA
slash_py-0.0.2.dist-info/WHEEL
slash_py-0.0.2.dist-info/entry_points.txt
slash_py-0.0.2.dist-info/top_level.txt
slash_py-0.0.2.dist-info/RECORD
