Metadata-Version: 2.4
Name: slash-py
Version: 0.0.2
Summary: SLURM Link Assistant Service Hub (SLASH) is a submodule for the python package sapp, dealing with the Internect connection problems.
License:                     GNU GENERAL PUBLIC LICENSE
Project-URL: Homepage, https://github.com/why-in-Shanghaitech/slash
Project-URL: Documentation, https://why-in-shanghaitech.github.io/slash/
Project-URL: Repository, https://github.com/why-in-Shanghaitech/slash.git
Project-URL: Bug Tracker, https://github.com/why-in-Shanghaitech/slash/issues
Classifier: Development Status :: 3 - Alpha
Classifier: Programming Language :: Python :: 3 :: Only
Classifier: Operating System :: POSIX :: Linux
Requires-Python: >=3.8
License-File: LICENSE
Requires-Dist: requests
Requires-Dist: ruamel.yaml
Requires-Dist: filelock
Requires-Dist: rich
Requires-Dist: psutil
Requires-Dist: Faker
Provides-Extra: docs
Requires-Dist: sphinx>=7.4.7; extra == "docs"
Requires-Dist: myst-parser; extra == "docs"
Requires-Dist: linkify-it-py; extra == "docs"
Requires-Dist: sphinx-autodoc2; extra == "docs"
Requires-Dist: furo; extra == "docs"
Requires-Dist: sphinxcontrib-autoprogram; extra == "docs"
Provides-Extra: test
Requires-Dist: pytest; extra == "test"
Dynamic: license-file
